MANIFEST.in
README
setup.py
django_ipgeo.egg-info/PKG-INFO
django_ipgeo.egg-info/SOURCES.txt
django_ipgeo.egg-info/dependency_links.txt
django_ipgeo.egg-info/requires.txt
django_ipgeo.egg-info/top_level.txt
ipgeo/__init__.py
ipgeo/admin.py
ipgeo/models.py
ipgeo/management/__init__.py
ipgeo/management/commands/__init__.py
ipgeo/management/commands/ipgeo_update.py