Metadata-Version: 1.0
Name: django-ipgeo
Version: 0.0.2
Summary: API to ipgeobase.ru database
Home-page: http://bitbucket.org/lorien/django-ipgeo/
Author: Grigoriy Petukhov
Author-email: lorien@lorien.name
License: BSD
Platform: UNKNOWN
Classifier: Development Status :: 4 - Beta
Classifier: Environment :: Web Environment
Classifier: Intended Audience :: Developers
Classifier: License :: OSI Approved :: BSD License
Classifier: Operating System :: OS Independent
Classifier: Programming Language :: Python
Classifier: Topic :: Software Development :: Libraries :: Python Modules
